autoLinker/__init__.py
autoLinker/file.py
autoLinker-1.0.2.dist-info/METADATA
autoLinker-1.0.2.dist-info/WHEEL
autoLinker-1.0.2.dist-info/license.txt
autoLinker-1.0.2.dist-info/top_level.txt
autoLinker-1.0.2.dist-info/RECORD
