Metadata-Version: 2.1
Name: autoLinker
Version: 1.0.2
Summary: A quick Linker
Home-page: UNKNOWN
Author: lin_zhe
Author-email: mcwyzlele@163.com
License: MIT License
Platform: any
License-File: license.txt
Requires-Dist: pyautogui
Requires-Dist: keyboard
